id_extractor/__init__.py
id_extractor/main.py
id_extractor/nets.py
id_extractor/utils/__init__.py
id_extractor/utils/download.py
id_extractor-0.0.7.dist-info/LICENSE.txt
id_extractor-0.0.7.dist-info/METADATA
id_extractor-0.0.7.dist-info/WHEEL
id_extractor-0.0.7.dist-info/top_level.txt
id_extractor-0.0.7.dist-info/RECORD
