Metadata-Version: 2.1
Name: id-extractor
Version: 0.0.7
Summary: innerverz package - id extractor
Author: Innerverz-by.JJY
Author-email: pensee0.0a@innerverz.com
Requires-Python: >=3.6
License-File: LICENSE.txt
Requires-Dist: Pillow
Requires-Dist: numpy
Requires-Dist: tqdm
Requires-Dist: gdown
